ocpi_pydantic-0.9.3.dist-info/METADATA
ocpi_pydantic-0.9.3.dist-info/WHEEL
ocpi_pydantic-0.9.3.dist-info/entry_points.txt
ocpi_pydantic-0.9.3.dist-info/licenses/LICENSE
ocpi_pydantic/__init__.py
ocpi_pydantic/v221/__init__.py
ocpi_pydantic/v221/base.py
ocpi_pydantic/v221/cdrs/__init__.py
ocpi_pydantic/v221/commands/__init__.py
ocpi_pydantic/v221/credentials/__init__.py
ocpi_pydantic/v221/enum.py
ocpi_pydantic/v221/locations/__init__.py
ocpi_pydantic/v221/locations/connector.py
ocpi_pydantic/v221/locations/evse.py
ocpi_pydantic/v221/locations/location.py
ocpi_pydantic/v221/sessions/__init__.py
ocpi_pydantic/v221/tariffs/__init__.py
ocpi_pydantic/v221/tokens/__init__.py
ocpi_pydantic/v221/versions/__init__.py
ocpi_pydantic-0.9.3.dist-info/RECORD
