Metadata-Version: 2.4
Name: ocpi-pydantic
Version: 0.9.3
Summary: OCPI Pydantic models
Keywords: OCPI,Pydantic
Author: Leon
License-Expression: MIT
License-File: LICENSE
Classifier: Development Status :: 5 - Production/Stable
Classifier: Environment :: Web Environment
Classifier: Intended Audience :: Developers
Classifier: Framework :: Pydantic :: 2
Classifier: Operating System :: OS Independent
Classifier: Programming Language :: Python :: 3.10
Classifier: Programming Language :: Python :: 3.11
Classifier: Programming Language :: Python :: 3.12
Classifier: Programming Language :: Python :: 3.13
Classifier: Programming Language :: Python :: 3.14
Classifier: Programming Language :: Python :: 3.15
Classifier: Topic :: Scientific/Engineering :: Interface Engine/Protocol Translator
Classifier: Topic :: Software Development :: Libraries :: Python Modules
Project-URL: homepage, https://github.com/OCPI-Python/ocpi-pydantic
Project-URL: source, https://github.com/OCPI-Python/ocpi-pydantic.git
Project-URL: issues, https://github.com/OCPI-Python/ocpi-pydantic/issues
Project-URL: changelog, https://github.com/OCPI-Python/ocpi-pydantic/blob/master/CHANGELOG.md
Project-URL: funding, https://github.com/OCPI-Python/ocpi-pydantic
Requires-Python: >=3.10
Requires-Dist: pydantic<3,>=2.12
